{
    "navBar": {
        "login": "Log in",
        "register": "Register",
        "dropDownNavMenu": {
            "controlPanel": "Control Panel",
            "profilePanel": "Profile",
            "logOutBtn": "Log Out"
        }
    },
    "loginPage": {
        "btnSend": "Sign in",
        "captionForm": "Sign in",
        "emailLabelText": "Your email",
        "passLabelText": "Your password",
        "errors": {
            "invalidEmail": "Invalid email address"
        }
    },
    "registerPage": {
        "btnSend": "Register",
        "captionForm": "Registration",
        "emailLabelText": "Your email",
        "passLabelText": "Your password",
        "passConfirmLabelText": "Confirm your password",
        "companyNameLabelText": "Company name",
        "errors": {
            "invalidEmail": "Invalid email address",
            "confirmPasswordError": "Passwords are not the same",
            "passwordTooLess": "Password must include more than 3 symbols",
            "companyIsAlreadyExist": "Sorry, but company with the same name is already exist"
        }
    },    
    "controlPanel": {
        "sideBarMenu": {
            "contacts": "Contacts",
            "payment": "Payment Info"
        },
        "contactsPan": {
            "table": {
                "givenName": "First Name",
                "middleName": "Middle Name",
                "familyName": "Family Name",
                "mail": "Email",
                "position": "Position",
                "subdivision": "Subdivision",
                "mobilePhone": "Mobile Phone",
                "workPhone": "Work Phone",
                "internalPhone": "Internal Phone",
                "avatar": "Avatar"
            },
            "tableMenu": {
                "edit": "Edit selected contact",
                "add": "Add contact",
                "delete": "Remove selected contact",
                "save": "Save contacts",
                "xls": "Load contacts from Excel file"
            },
            "contactEdit": {
                "editTitle": "Edit contact",
                "addTitle": "Create contact",
                "save": "Save Changes",
                "cancel": "Cancel",
                "uploadPhoto": "Upload a different photo..."
            }
        }
    },
    "profilePanel": {
        "sideBarMenu": {
            "profile": "Profile Info",
            "passwordManage": "Password Change"
        },
        "profileContent": {
            "companyLabel": "Company",
            "emailLabel": "Login",
            "registerDateLabel": "Register Date",
            "phoneNumberLabel": "Phone Number"
        },
        "passwordContent": {
            "oldPasswordLabel": "Old password",
            "newPasswordLabel": "New password",
            "confirmNewPasswordLabel": "Confirm new password",
            "btnSend": "Change password"
        }
    }
}